auth_sso_client/__init__.py
auth_sso_client/config.py
auth_sso_client/core.py
auth_sso_client/errors.py
auth_sso_client/fastapi.py
auth_sso_client/models.py
auth_sso_client-0.1.2.dist-info/METADATA
auth_sso_client-0.1.2.dist-info/WHEEL
auth_sso_client-0.1.2.dist-info/RECORD
