Metadata-Version: 2.4
Name: auth_sso_client
Version: 0.1.2
Summary: Auth server WeCom SSO client for Python/FastAPI.
Requires-Python: >=3.12
Requires-Dist: fastapi>=0.116.1
Requires-Dist: httpx>=0.27.0
